gs1_gpc/__init__.py
gs1_gpc/callbacks.py
gs1_gpc/cli.py
gs1_gpc/db.py
gs1_gpc/downloader.py
gs1_gpc/exporter.py
gs1_gpc/models.py
gs1_gpc/parser.py
gs1_gpc/tests/__init__.py
gs1_gpc/tests/test_db.py
gs1_gpc-0.3.3.dist-info/LICENSE
gs1_gpc-0.3.3.dist-info/METADATA
gs1_gpc-0.3.3.dist-info/WHEEL
gs1_gpc-0.3.3.dist-info/entry_points.txt
gs1_gpc-0.3.3.dist-info/top_level.txt
gs1_gpc-0.3.3.dist-info/RECORD
