Metadata-Version: 2.1
Name: gs1-gpc
Version: 0.3.3
Summary: A tool for importing GS1 Global Product Classification (GPC) data into SQL databases
Author: Michael McGarrah
Author-email: Michael McGarrah <mcgarrah@gmail.com>
License: MIT
Project-URL: Homepage, https://github.com/mcgarrah/gs1_gpc_python
Project-URL: Bug Tracker, https://github.com/mcgarrah/gs1_gpc_python/issues
Project-URL: Repository, https://github.com/mcgarrah/gs1_gpc_python
Project-URL: Documentation, https://gs1-gpc.readthedocs.io/
Classifier: Development Status :: 4 - Beta
Classifier: Intended Audience :: Developers
Classifier: Programming Language :: Python :: 3
Classifier: Programming Language :: Python :: 3.8
Classifier: Programming Language :: Python :: 3.9
Classifier: Programming Language :: Python :: 3.10
Classifier: Programming Language :: Python :: 3.11
Classifier: Programming Language :: Python :: 3.12
Requires-Python: >=3.8
License-File: LICENSE
Requires-Dist: click>=8.0.0
Requires-Dist: gpcc>=1.1.0
Provides-Extra: dev
Requires-Dist: pytest>=6.0; extra == "dev"
Requires-Dist: pytest-cov>=2.10; extra == "dev"
Requires-Dist: black>=22.3; extra == "dev"
Requires-Dist: flake8>=3.9; extra == "dev"
Requires-Dist: mypy>=0.910; extra == "dev"
Requires-Dist: isort>=5.0; extra == "dev"
Requires-Dist: bandit>=1.7; extra == "dev"
Requires-Dist: pre-commit>=2.13; extra == "dev"
Provides-Extra: docs
Requires-Dist: sphinx>=8.2.3; extra == "docs"
Requires-Dist: sphinx-rtd-theme>=3.0.2; extra == "docs"
Provides-Extra: postgresql
Requires-Dist: psycopg2-binary>=2.9.0; extra == "postgresql"
